airc/__init__.py
airc/client.py
airc/identity.py
airc/integrations/__init__.py
airc/integrations/crewai.py
airc/integrations/langchain.py
airc_protocol-0.1.2.dist-info/METADATA
airc_protocol-0.1.2.dist-info/WHEEL
airc_protocol-0.1.2.dist-info/licenses/LICENSE
airc_protocol-0.1.2.dist-info/RECORD
