Metadata-Version: 2.4
Name: airc-protocol
Version: 0.1.2
Summary: Minimal Python client for AIRC protocol - Agent Identity & Relay Communication
Project-URL: Homepage, https://airc.chat
Project-URL: Documentation, https://airc.chat/AIRC_SPEC.md
Project-URL: Repository, https://github.com/brightseth/airc-python
Project-URL: Issues, https://github.com/brightseth/airc-python/issues
Author-email: Seth Goldstein <seth@sethgoldstein.com>
License-Expression: MIT
License-File: LICENSE
Keywords: agents,ai,airc,communication,protocol
Classifier: Development Status :: 3 - Alpha
Classifier: Intended Audience :: Developers
Classifier: License :: OSI Approved :: MIT License
Classifier: Programming Language :: Python :: 3
Classifier: Programming Language :: Python :: 3.9
Classifier: Programming Language :: Python :: 3.10
Classifier: Programming Language :: Python :: 3.11
Classifier: Programming Language :: Python :: 3.12
Classifier: Topic :: Communications
Classifier: Topic :: Software Development :: Libraries :: Python Modules
Requires-Python: >=3.9
Requires-Dist: cryptography>=41.0.0
Provides-Extra: all
Requires-Dist: crewai>=0.1.0; extra == 'all'
Requires-Dist: langchain-core>=0.1.0; extra == 'all'
Requires-Dist: pyautogen>=0.2.0; extra == 'all'
Provides-Extra: autogen
Requires-Dist: pyautogen>=0.2.0; extra == 'autogen'
Provides-Extra: crewai
Requires-Dist: crewai>=0.1.0; extra == 'crewai'
Provides-Extra: dev
Requires-Dist: pytest-asyncio>=0.21.0; extra == 'dev'
Requires-Dist: pytest>=7.0.0; extra == 'dev'
Provides-Extra: langchain
Requires-Dist: langchain-core>=0.1.0; extra == 'langchain'
